oxylabs_ai_studio_mcp/__init__.py
oxylabs_ai_studio_mcp/server.py
oxylabs_ai_studio_mcp-0.1.4.dist-info/METADATA
oxylabs_ai_studio_mcp-0.1.4.dist-info/WHEEL
oxylabs_ai_studio_mcp-0.1.4.dist-info/entry_points.txt
oxylabs_ai_studio_mcp-0.1.4.dist-info/licenses/LICENSE
oxylabs_ai_studio_mcp-0.1.4.dist-info/RECORD
