Metadata-Version: 2.4
Name: oxylabs-ai-studio-mcp
Version: 0.1.4
Summary: oxylabs ai studio mcp server
License-File: LICENSE
Keywords: ai,mcp,oxylabs,studio
Requires-Python: >=3.10
Requires-Dist: mcp[cli]>=1.9.4
Requires-Dist: oxylabs-ai-studio>=0.2.7
Requires-Dist: pydantic>=2.11.5
Requires-Dist: python-dotenv>=1.1.0
